AD20/ADgraph.py
AD20/ADmath.py
AD20/ADnum.py
AD20/__init__.py
Tests/__init__.py
Tests/test_AD20.py
AD20-0.0.2.dist-info/LICENSE
AD20-0.0.2.dist-info/METADATA
AD20-0.0.2.dist-info/WHEEL
AD20-0.0.2.dist-info/top_level.txt
AD20-0.0.2.dist-info/RECORD
